{
  "name": "WeatherData",
  "plural": "WeatherData",
  "base": "PersistedModel",
  "idInjection": true,
  "options": {
    "validateUpsert": true
  },
  "mixins": {
    "TimeStamp": {
      "createdAt": "createdOn",
      "updatedAt": "updatedOn",
      "required": false,
      "validateUpsert": true,
      "silenceWarnings": false
    }
  },
  "properties": {
    "data": {
      "type": "object"
    }
  },
  "validations": [],
  "relations": {
    "station": {
      "type": "belongsTo",
      "model": "Station",
      "foreignKey": ""
    }
  },
  "acls": [],
  "methods": {}
}
